{
  "swagger": "2.0",
  "info": {
    "version": "1.0.0",
    "title": "My API",
    "description": "Documentation automatically generated by the <b>swagger-autogen</b> module."
  },
  "host": "localhost:2025",
  "basePath": "/api",
  "schemes": [
    "http",
    "https"
  ],
  "securityDefinitions": {
    "bearerAuth": {
      "type": "apiKey",
      "name": "authorization",
      "scheme": "bearer",
      "in": "header"
    }
  },
  "consumes": [
    "application/json"
  ],
  "produces": [
    "application/json"
  ],
  "paths": {
    "/test": {
      "get": {
        "description": "",
        "responses": {
          "200": {
            "description": "OK"
          }
        }
      }
    }
  },
  "security": [
    {
      "bearerAuth": []
    }
  ]
}